flask_lab.py
flask_lab-0.0.3.dist-info/entry_points.txt
flask_lab-0.0.3.dist-info/WHEEL
flask_lab-0.0.3.dist-info/METADATA
flask_lab-0.0.3.dist-info/RECORD
