Metadata-Version: 2.1
Name: flask-lab
Version: 0.0.3
Summary: Django-admin for flask with restful API.
Home-page: https://github.com/yifeikong/flask-lab
License: MIT
Author: Yifei Kong
Author-email: kongyifei@gmail.com
Requires-Python: >=3.6,<4.0
Classifier: License :: OSI Approved :: MIT License
Classifier: Programming Language :: Python :: 3
Classifier: Programming Language :: Python :: 3.6
Classifier: Programming Language :: Python :: 3.7
Classifier: Programming Language :: Python :: 3.8
Requires-Dist: flask (>=1.1.1,<2.0.0)
Requires-Dist: peewee (>=3.13,<4.0)
Project-URL: Repository, https://github.com/yifeikong/flask-lab
